{
	"actionscope": "https://www.googleapis.com/auth/admin.directory.device.mobile",
	"apiqueryorderby": "name",
	"datastorequeryorderby": "Domain",
	"dsnamekey": "MobileDevice",
	"globaldebug": true,
	"projectid": "yourgcpprojectname",
	"remotewipetype": "admin_account_wipe",
	"searchscope": "https://www.googleapis.com/auth/admin.directory.device.mobile.readonly",
	"searchtype": "all",
	"sheetcreds": "credentials_yourgsuitedomain.com.json",
	"sheetid": "yourgooglesheetidgoeshere",
	"sheetscope": "https://www.googleapis.com/auth/spreadsheets",
	"sheetwho": "username@yourgsuitedomain.com",
	"version": "0.8",
	"domains": [
		{
			"domainname": "yourgsuitedomain.com",
			"companyid": "C0123abcD",
			"adminuser": "username@yourgsuitedomain.com",
			"credentialsfile": "/path/to/credentials_yourgsuitedomain.com.json"
		}
	]
}

